pythings/__init__.py
pythings-0.0.1.dist-info/METADATA
pythings-0.0.1.dist-info/WHEEL
pythings-0.0.1.dist-info/top_level.txt
pythings-0.0.1.dist-info/RECORD
